heimdall/__init__.py
heimdall/bifrost/__init__.py
heimdall/bifrost/bqconnection.py
heimdall/bifrost/feature_data.py
heimdall/bifrost/utils/__init__.py
heimdall/bifrost/utils/data_structures.py
heimdall/cli/__init__.py
heimdall/cli/main.py
heimdall/gjallarhorn/__init__.py
heimdall/gjallarhorn/main.py
heimdall/gjallarhorn/streamlit/__init__.py
heimdall/gjallarhorn/streamlit/drift_monitor.py
heimdall/gjallarhorn/streamlit/home.py
heimdall/gjallarhorn/streamlit/performance_monitor.py
heimdall/gjallarhorn/streamlit/systems_monitor.py
heimdall/gjallarhorn/streamlit/utils/__init__.py
heimdall/gjallarhorn/streamlit/utils/constants.py
heimdall/gjallarhorn/streamlit/utils/graph.py
heimdall/gjallarhorn/streamlit/utils/meta.py
heimdall/gulltoppr/__init__.py
heimdall/gulltoppr/drift_monitor/__init__.py
heimdall/gulltoppr/drift_monitor/algorithms/__init__.py
heimdall/gulltoppr/drift_monitor/algorithms/algorithms.py
heimdall/gulltoppr/drift_monitor/algorithms/helper_functions.py
heimdall/gulltoppr/drift_monitor/main.py
heimdall/gulltoppr/main.py
heimdall/gulltoppr/performance_monitor/__init__.py
heimdall/gulltoppr/performance_monitor/main.py
heimdall/gulltoppr/performance_monitor/metrics/__init__.py
heimdall/gulltoppr/performance_monitor/metrics/metrics.py
heimdall/gulltoppr/systems_monitor/__init__.py
heimdall/gulltoppr/systems_monitor/main.py
heimdall/gulltoppr/systems_monitor/metrics/__init__.py
heimdall/gulltoppr/systems_monitor/metrics/helper_functions.py
heimdall/gulltoppr/systems_monitor/metrics/metrics.py
heimdall/main.py
heimdall/utils/__init__.py
heimdall/utils/coalesce.py
heimdall/utils/environmental_vars.py
heimdall/utils/errors.py
heimdall/utils/histograms.py
heimdall/utils/logging.py
heimdall/utils/yaml_helper.py
heimdall_ml-1.1.15.dist-info/entry_points.txt
heimdall_ml-1.1.15.dist-info/LICENSE.md
heimdall_ml-1.1.15.dist-info/WHEEL
heimdall_ml-1.1.15.dist-info/METADATA
heimdall_ml-1.1.15.dist-info/RECORD
