Metadata-Version: 2.1
Name: heimdall-ml
Version: 1.1.15
Summary: Package to monitor machine learning models using .yml files
License: Apache-2.0
Author: Ben Hicks
Author-email: bhicks@uw.co.uk
Requires-Python: >=3.8,<3.9.7
Classifier: License :: OSI Approved :: Apache Software License
Classifier: Programming Language :: Python :: 3
Classifier: Programming Language :: Python :: 3.8
Classifier: Programming Language :: Python :: 3.9
Requires-Dist: PyYAML (>=6.0,<7.0)
Requires-Dist: aif360 (>=0.5.0,<0.6.0)
Requires-Dist: click (>=8.1.3,<9.0.0)
Requires-Dist: colorlog (==6.7.0)
Requires-Dist: google-cloud-bigquery (==3.3.2)
Requires-Dist: numpy (==1.23.2)
Requires-Dist: pandas (>=1.4.4,<2.0.0)
Requires-Dist: pandas-gbq (==0.17.8)
Requires-Dist: plotly (==5.10.0)
Requires-Dist: redis (>=4.3.4,<5.0.0)
Requires-Dist: schedule (>=1.1.0,<2.0.0)
Requires-Dist: scikit-learn (>=1.1.2,<2.0.0)
Requires-Dist: scipy (>=1.9.1,<2.0.0)
Requires-Dist: slack-sdk (==3.18.3)
Requires-Dist: streamlit (==1.12.2)
Requires-Dist: streamlit-aggrid (>=0.3.3,<0.4.0)
Requires-Dist: streamlit-option-menu (>=0.3.2,<0.4.0)
